{
    "total_responses": {
      "total": {
        "0": 11521
      }
    },
    "total_by_experience": {
      "Menos de 1 ano": 2256,
      "Entre 1 e 2 anos": 2182,
      "Entre 2 e 4 anos": 2559,
      "Entre 4 e 6 anos": 1389,
      "Entre 6 e 8 anos": 726,
      "Entre 8 e 10 anos": 663,
      "Entre 10 e 15 anos": 985,
      "Entre 15 e 20 anos": 410,
      "Mais de 20 anos": 351
    },
    "total_by_level": {
      "Est\u00e1gio": 933,
      "J\u00fanior": 3680,
      "Pleno": 3577,
      "S\u00eanior": 2994,
      "Outro": 337
    },
    "total_by_type": {
      "Front-End": 1751,
      "Back-End": 3199,
      "Full Stack": 4582,
      "DevOps": 245,
      "Mobile": 688,
      "Full Cycle": 395,
      "Outro": 661
    },
    "total_stack_satisfaction": {
      "Sim": 9538,
      "N\u00e3o": 1983
    },
    "total_by_salary": {
      "Menos de 1.000": 240,
      "Entre 1.001 e 2.000": 1118,
      "Entre 2.001 e 3.000": 1309,
      "Entre 3.001 e 4.000": 1284,
      "Entre 4.001 e 5.000": 1152,
      "Entre 5.001 e 6.000": 1046,
      "Entre 6.001 e 7.000": 830,
      "Entre 7.001 e 9.000": 1303,
      "Entre 9.001 e 12.000": 1381,
      "Entre 12.001 e 15.000": 766,
      "Entre 15.001 e 20.000": 529,
      "Entre 20.001 e 30.000": 310,
      "Entre 30.001 e 40.000": 137,
      "Entre 40.001 e 50.000": 61,
      "Acima de 50.000": 55
    },
    "total_by_work_model": {
      "CLT": 7871,
      "PJ": 2582,
      "Outro": 1068
    },
    "total_foreign_job_in_brazil": {
      "Sim": 1031,
      "N\u00e3o": 10490
    },
    "total_income_foreign_currency": {
      "Sim": 1551,
      "N\u00e3o": 9970
    },
    "total_income_goals_satisfaction": {
      "Muito safisfeito": 1322,
      "Satisfeito": 5471,
      "Indiferente": 1404,
      "Insatisfeito": 2890,
      "Muito insatisfeito": 434
    },
    "total_work_model_location": {
      "Presencial": 1220,
      "Remoto": 8647,
      "H\u00edbrido": 1654
    },
    "total_work_model_location_desire": {
      "Presencial": 241,
      "Remoto": 8385,
      "H\u00edbrido": 2895
    },
    "total_by_gender": {
      "Masculino": 10613,
      "Feminino": 865,
      "Prefiro n\u00e3o informar": 43
    },
    "total_by_age": {
      "de 13 a 17 anos": 62,
      "de 18 a 24 anos": 3921,
      "de 25 a 34 anos": 5590,
      "de 35 a 44 anos": 1640,
      "de 45 a 54 anos": 274,
      "de 55 a 64 anos": 31,
      "a partir de 65 anos": 3
    },
    "total_english_level": {
      "Nenhum": 233,
      "B\u00e1sico": 3608,
      "Intermedi\u00e1rio": 5329,
      "Fluente": 2351
    },
    "total_english_conversation": {
      "Sim": 4153,
      "N\u00e3o": 7368
    },
    "total_another_country_moving_plans": {
      "Sim, em at\u00e9 1 ano": 719,
      "Sim, para os pr\u00f3ximos 5 anos": 4223,
      "Sim, mas levar\u00e1 mais de 5 anos": 2157,
      "N\u00e3o": 4231,
      "J\u00e1 estou no exterior": 191
    },
    "total_career_transition": {
      "Sim, fiz transi\u00e7\u00e3o de carreira": 4026,
      "Sim, mas ainda estou em transi\u00e7\u00e3o de carreira": 353,
      "N\u00e3o": 7142
    },
    "total_residence_region": {
      "Regi\u00e3o Metropolitana": 2991,
      "Capital": 4397,
      "Interior": 4133
    },
    "total_by_brazil_uf": {
      "Acre (AC)": 13,
      "Alagoas (AL)": 77,
      "Amap\u00e1 (AP)": 4,
      "Amazonas (AM)": 102,
      "Bahia (BA)": 342,
      "Cear\u00e1 (CE)": 434,
      "Distrito Federal (DF)": 332,
      "Esp\u00edrito Santo (ES)": 206,
      "Goi\u00e1s (GO)": 254,
      "Maranh\u00e3o (MA)": 88,
      "Mato Grosso (MT)": 98,
      "Mato Grosso do Sul (MS)": 131,
      "Minas Gerais (MG)": 1275,
      "Par\u00e1 (PA)": 122,
      "Para\u00edba (PB)": 181,
      "Paran\u00e1 (PR)": 860,
      "Pernambuco (PE)": 373,
      "Piau\u00ed (PI)": 70,
      "Rio de Janeiro (RJ)": 812,
      "Rio Grande do Norte (RN)": 147,
      "Rio Grande do Sul (RS)": 729,
      "Rond\u00f4nia (RO)": 50,
      "Roraima (RR)": 4,
      "Santa Catarina (SC)": 770,
      "S\u00e3o Paulo (SP)": 3701,
      "Sergipe (SE)": 97,
      "Tocantins (TO)": 56
    },
    "total_outside_brazil": {
      "Fora do Brasil": 193
    },
    "total_back_to_brazil": {
      "Sim": 21,
      "N\u00e3o": 122,
      "Talvez": 50
    },
    "total_by_graduation": {
      "N\u00e3o fiz faculdade": 777,
      "Superior em andamento": 3020,
      "Superior incompleto": 1221,
      "Superior completo": 4657,
      "P\u00f3s-gradua\u00e7\u00e3o / MBA": 1541,
      "Mestrado / Doutorado": 305
    },
    "total_main_knowledge_source": {
      "Cursos online ou Certifica\u00e7\u00f5es": 4182,
      "V\u00eddeos, Artigos e Blogs (YouTube, Dev.to, Medium, etc)": 5480,
      "Eventos, bootcamps, imers\u00f5es, maratonas e/ou hackathons": 388,
      "F\u00f3runs e/ou Comunidades online (Stack Overflow, Discord, Telegram, etc)": 686,
      "Faculdade": 111,
      "Livros e eBooks": 259,
      "Colegas de trabalho ou mentores": 415
    },
    "total_by_foreign_countries": {
      "PORTUGAL": 75,
      "CANAD\u00c1": 18,
      "ALEMANHA": 14,
      "IRLANDA": 9,
      "JAP\u00c3O": 7,
      "ANGOLA": 7,
      "EUA": 6,
      "HOLANDA": 6,
      "INGLATERRA": 5,
      "PA\u00cdSES BAIXOS": 5,
      "IT\u00c1LIA": 4,
      "ESPANHA": 3,
      "PARAGUAI": 3,
      "REINO UNIDO": 3,
      "LUXEMBURGO": 3,
      "MO\u00c7AMBIQUE": 2,
      "B\u00c9LGICA": 2,
      "ARGENTINA": 2,
      "FRAN\u00c7A": 2,
      "LIECHTENSTEIN": 1,
      "\u00c1USTRIA": 1,
      "URUGUAI": 1,
      "SU\u00cd\u00c7A": 1,
      "ESC\u00d3CIA": 1,
      "DINAMARCA": 1,
      "AUSTRALIA": 1,
      "EL SALVADOR": 1,
      "COL\u00d4MBIA": 1,
      "NOVA ZEL\u00c2NDIA": 1,
      "MALTA": 1,
      "N\u00d4MADE": 1,
      "MONTENEGRO": 1
    },
    "total_by_platforms": {
      "Web": 4243,
      "Mobile": 2831,
      "Desktop": 2285,
      "Embarcados": 495,
      "Outra": 613
    },
    "total_by_languages": {
      "JAVASCRIPT": 3557.0,
      "JAVA": 2048.0,
      "C#": 1614.0,
      "PHP": 1227.0,
      "PYTHON": 881.0,
      "TYPESCRIPT": 464.0,
      "KOTLIN": 269.0,
      "DART": 234.0,
      "DELPHI": 194.0,
      "RUBY": 185.0,
      "GO": 158.0,
      "SWIFT": 133.0,
      "SQL": 91.0,
      ".NET (CORE)": 89.0,
      "BUBBLE": 85.0,
      "C++": 72.0,
      "APEX": 61.0,
      "C": 49.0,
      "PL/SQL": 43.0,
      "ELIXIR": 39.0,
      "ADVPL": 36.0,
      "CLOJURE": 22.0,
      "ABAP": 20.0,
      "VISUAL BASIC 6": 17.0,
      "HTML": 16.0,
      "NO CODE": 15.0,
      "POWER FX": 14.0,
      "VB.NET": 12.0,
      "COBOL": 9.0,
      "SHELL": 9.0,
      "PASCAL": 9.0,
      "BASH": 8.0,
      "PROGRESS": 8.0,
      "SCALA": 8.0,
      "ASP 3": 7.0,
      "RUST": 7.0,
      "CSS": 7.0,
      "GENEXUS": 6.0,
      "LUA": 6.0,
      "GROOVY": 6.0,
      "VBA": 6.0,
      "SHELL SCRIPT": 5.0,
      "POWER PLATFORM": 4.0,
      "MAKER": 4.0,
      "OUTSYSTEMS": 4.0,
      "UNIFACE": 3.0,
      "PERL": 3.0,
      "YAML": 3.0,
      "OBJECT PASCAL": 3.0,
      "SQL SERVER": 3.0,
      "POWERSHELL": 3.0,
      "REACT": 3.0,
      "TERRAFORM": 3.0,
      "CENTURA": 3.0,
      "R": 3.0,
      "BI": 2.0,
      "POWERAPPS": 2.0,
      "SPARK": 2.0,
      "SELENIUM": 2.0,
      "HCL": 2.0
    },
    "total_by_frameworks": {
      "REACT": 2958.0,
      "NODE.JS": 2361.0,
      "ANGULAR": 1826.0,
      "VUE.JS": 962.0,
      "SPRING": 810.0,
      "LARAVEL": 772.0,
      ".NET": 676.0,
      "FLUTTER": 629.0,
      "SPRING BOOT": 545.0,
      "REACT NATIVE": 474.0,
      "DJANGO": 325.0,
      "NEXT.JS": 288.0,
      "NEST.JS": 253.0,
      ".NET CORE": 219.0,
      "RAILS": 208.0,
      "DOCKER": 202.0,
      "AWS": 198.0,
      "JQUERY": 180.0,
      "FLASK": 163.0,
      "BOOTSTRAP": 159.0,
      "EXPRESS": 124.0,
      "MYSQL": 120.0,
      "IONIC": 103.0,
      "ANGULARJS": 94.0,
      "MONGODB": 93.0,
      "KUBERNETES": 90.0,
      "ANDROID": 84.0,
      "KAFKA": 81.0,
      "CODEIGNITER": 81.0,
      "FASTAPI": 75.0,
      "ASP.NET": 73.0,
      "GIT": 73.0,
      "PANDAS": 69.0,
      "QUARKUS": 69.0,
      "SQL SERVER": 66.0,
      "SYMPHONY": 60.0,
      "WORDPRESS": 60.0,
      "GRAPHQL": 59.0,
      "HIBERNATE": 59.0,
      "POSTGRESQL": 55.0,
      ".NET FRAMEWORK": 55.0,
      "KOTLIN": 54.0,
      "JSF": 53.0,
      "BUBBLE": 49.0,
      "XAMARIN": 44.0,
      "REACT-NATIVE": 43.0,
      "ASP.NET CORE": 41.0,
      "AZURE": 40.0,
      "SPRING FRAMEWORK": 40.0,
      "POSTGRES": 39.0,
      "SPARK": 38.0,
      "LUMEN": 36.0,
      "RABBITMQ": 35.0,
      "NUXT": 35.0,
      "PHOENIX": 34.0,
      "SERVERLESS": 33.0,
      "TERRAFORM": 34.0,
      "ORACLE": 34.0,
      "REDIS": 34.0,
      "REACT JS": 34.0
    },
    "salary_by_experience": {
      "columns": [
        "Menos de 1 ano",
        "Entre 1 e 2 anos",
        "Entre 2 e 4 anos",
        "Entre 4 e 6 anos",
        "Entre 6 e 8 anos",
        "Entre 8 e 10 anos",
        "Entre 10 e 15 anos",
        "Entre 15 e 20 anos",
        "Mais de 20 anos"
      ],
      "index": [
        "Menos de 1.000",
        "Entre 1.001 e 2.000",
        "Entre 2.001 e 3.000",
        "Entre 3.001 e 4.000",
        "Entre 4.001 e 5.000",
        "Entre 5.001 e 6.000",
        "Entre 6.001 e 7.000",
        "Entre 7.001 e 9.000",
        "Entre 9.001 e 12.000",
        "Entre 12.001 e 15.000",
        "Entre 15.001 e 20.000",
        "Entre 20.001 e 30.000",
        "Entre 30.001 e 40.000",
        "Entre 40.001 e 50.000",
        "Acima de 50.000"
      ],
      "data": [
        [174.0, 48, 14, 1, null, null, 2, null, 1],
        [691.0, 298, 97, 16, 4.0, 6.0, 2, 3.0, 1],
        [584.0, 440, 210, 38, 18.0, 5.0, 7, 4.0, 3],
        [396.0, 440, 332, 63, 19.0, 18.0, 9, 4.0, 3],
        [206.0, 336, 384, 99, 45.0, 28.0, 35, 9.0, 10],
        [120.0, 240, 372, 137, 68.0, 44.0, 35, 17.0, 13],
        [37.0, 141, 301, 158, 69.0, 45.0, 44, 16.0, 19],
        [27.0, 130, 400, 305, 121.0, 97.0, 131, 56.0, 36],
        [9.0, 66, 247, 309, 159.0, 172.0, 252, 89.0, 78],
        [3.0, 14, 103, 110, 97.0, 102.0, 192, 84.0, 61],
        [4.0, 10, 47, 79, 57.0, 77.0, 132, 67.0, 56],
        [null, 10, 30, 49, 36.0, 36.0, 74, 35.0, 40],
        [4.0, 2, 16, 17, 20.0, 16.0, 33, 14.0, 15],
        [null, 5, 3, 5, 5.0, 13.0, 20, 5.0, 5],
        [1.0, 2, 3, 3, 8.0, 4.0, 17, 7.0, 10]
      ]
    },
    "salary_by_level": {
      "columns": ["Est\u00e1gio", "J\u00fanior", "Pleno", "S\u00eanior", "Outro"],
      "index": [
        "Menos de 1.000",
        "Entre 1.001 e 2.000",
        "Entre 2.001 e 3.000",
        "Entre 3.001 e 4.000",
        "Entre 4.001 e 5.000",
        "Entre 5.001 e 6.000",
        "Entre 6.001 e 7.000",
        "Entre 7.001 e 9.000",
        "Entre 9.001 e 12.000",
        "Entre 12.001 e 15.000",
        "Entre 15.001 e 20.000",
        "Entre 20.001 e 30.000",
        "Entre 30.001 e 40.000",
        "Entre 40.001 e 50.000",
        "Acima de 50.000"
      ],
      "data": [
        [185.0, 31.0, 7, 1, 16],
        [569.0, 487.0, 37, 4, 21],
        [142.0, 984.0, 132, 10, 41],
        [18.0, 974.0, 269, 17, 6],
        [6.0, 601.0, 480, 57, 8],
        [6.0, 330.0, 616, 87, 7],
        [1.0, 146.0, 535, 142, 6],
        [null, 81.0, 811, 395, 16],
        [3.0, 25.0, 447, 874, 32],
        [null, 4.0, 103, 602, 57],
        [null, 10.0, 60, 385, 74],
        [null, 3.0, 50, 220, 37],
        [null, 3.0, 20, 103, 11],
        [1.0, null, 7, 51, 2],
        [2.0, 1.0, 3, 46, 3]
      ]
    },
    "salary_by_type": {
      "columns": [
        "Front-End",
        "Back-End",
        "Full Stack",
        "DevOps",
        "Mobile",
        "Full Cycle",
        "Outro"
      ],
      "index": [
        "Menos de 1.000",
        "Entre 1.001 e 2.000",
        "Entre 2.001 e 3.000",
        "Entre 3.001 e 4.000",
        "Entre 4.001 e 5.000",
        "Entre 5.001 e 6.000",
        "Entre 6.001 e 7.000",
        "Entre 7.001 e 9.000",
        "Entre 9.001 e 12.000",
        "Entre 12.001 e 15.000",
        "Entre 15.001 e 20.000",
        "Entre 20.001 e 30.000",
        "Entre 30.001 e 40.000",
        "Entre 40.001 e 50.000",
        "Acima de 50.000"
      ],
      "data": [
        [63, 59, 81, 1, 8, 3, 25],
        [225, 275, 459, 27, 54, 15, 63],
        [277, 310, 534, 24, 56, 27, 81],
        [244, 319, 538, 24, 80, 16, 63],
        [173, 312, 495, 17, 66, 20, 69],
        [165, 309, 412, 22, 65, 21, 52],
        [114, 251, 334, 11, 54, 21, 45],
        [162, 399, 517, 35, 79, 39, 72],
        [152, 448, 514, 28, 98, 75, 66],
        [64, 248, 280, 21, 57, 50, 46],
        [52, 146, 192, 12, 37, 52, 38],
        [29, 70, 126, 13, 16, 35, 21],
        [20, 34, 43, 7, 9, 12, 12],
        [8, 9, 28, 1, 5, 5, 5],
        [3, 10, 29, 2, 4, 4, 3]
      ]
    },
    "salary_by_work_model": {
      "columns": ["CLT", "PJ", "Outro"],
      "index": [
        "Menos de 1.000",
        "Entre 1.001 e 2.000",
        "Entre 2.001 e 3.000",
        "Entre 3.001 e 4.000",
        "Entre 4.001 e 5.000",
        "Entre 5.001 e 6.000",
        "Entre 6.001 e 7.000",
        "Entre 7.001 e 9.000",
        "Entre 9.001 e 12.000",
        "Entre 12.001 e 15.000",
        "Entre 15.001 e 20.000",
        "Entre 20.001 e 30.000",
        "Entre 30.001 e 40.000",
        "Entre 40.001 e 50.000",
        "Acima de 50.000"
      ],
      "data": [
        [67, 24, 149],
        [631, 140, 347],
        [981, 217, 111],
        [990, 244, 50],
        [905, 204, 43],
        [812, 188, 46],
        [632, 159, 39],
        [995, 250, 58],
        [995, 317, 69],
        [481, 246, 39],
        [253, 243, 33],
        [86, 189, 35],
        [28, 91, 18],
        [10, 37, 14],
        [5, 33, 17]
      ]
    },
    "salary_by_gender": {
      "columns": ["Masculino", "Feminino", "Prefiro n\u00e3o informar"],
      "index": [
        "Menos de 1.000",
        "Entre 1.001 e 2.000",
        "Entre 2.001 e 3.000",
        "Entre 3.001 e 4.000",
        "Entre 4.001 e 5.000",
        "Entre 5.001 e 6.000",
        "Entre 6.001 e 7.000",
        "Entre 7.001 e 9.000",
        "Entre 9.001 e 12.000",
        "Entre 12.001 e 15.000",
        "Entre 15.001 e 20.000",
        "Entre 20.001 e 30.000",
        "Entre 30.001 e 40.000",
        "Entre 40.001 e 50.000",
        "Acima de 50.000"
      ],
      "data": [
        [226, 12, 2.0],
        [995, 119, 4.0],
        [1166, 136, 7.0],
        [1178, 100, 6.0],
        [1028, 124, null],
        [929, 111, 6.0],
        [768, 61, 1.0],
        [1208, 88, 7.0],
        [1314, 63, 4.0],
        [745, 20, 1.0],
        [514, 14, 1.0],
        [298, 10, 2.0],
        [134, 2, 1.0],
        [58, 3, null],
        [52, 2, 1.0]
      ]
    },
    "salary_by_age": {
      "columns": [
        "de 13 a 17 anos",
        "de 18 a 24 anos",
        "de 25 a 34 anos",
        "de 35 a 44 anos",
        "de 45 a 54 anos",
        "de 55 a 64 anos",
        "a partir de 65 anos"
      ],
      "index": [
        "Menos de 1.000",
        "Entre 1.001 e 2.000",
        "Entre 2.001 e 3.000",
        "Entre 3.001 e 4.000",
        "Entre 4.001 e 5.000",
        "Entre 5.001 e 6.000",
        "Entre 6.001 e 7.000",
        "Entre 7.001 e 9.000",
        "Entre 9.001 e 12.000",
        "Entre 12.001 e 15.000",
        "Entre 15.001 e 20.000",
        "Entre 20.001 e 30.000",
        "Entre 30.001 e 40.000",
        "Entre 40.001 e 50.000",
        "Acima de 50.000"
      ],
      "data": [
        [20.0, 147, 57, 9, 6, 1.0, null],
        [26.0, 729, 306, 47, 9, 1.0, null],
        [6.0, 708, 498, 92, 3, 2.0, null],
        [3.0, 586, 566, 112, 15, 2.0, null],
        [3.0, 440, 588, 105, 13, 1.0, 2.0],
        [1.0, 348, 572, 110, 13, 2.0, null],
        [1.0, 242, 448, 111, 25, 3.0, null],
        [1.0, 309, 734, 207, 42, 10.0, null],
        [null, 223, 773, 333, 48, 4.0, null],
        [null, 78, 432, 215, 39, 2.0, null],
        [null, 55, 288, 152, 34, null, null],
        [null, 29, 174, 93, 13, 1.0, null],
        [null, 16, 84, 30, 7, null, null],
        [null, 5, 43, 10, 2, null, 1.0],
        [1.0, 6, 27, 14, 5, 2.0, null]
      ]
    },
    "salary_by_brazil_uf": {
      "columns": [
        "Acre (AC)",
        "Alagoas (AL)",
        "Amap\u00e1 (AP)",
        "Amazonas (AM)",
        "Bahia (BA)",
        "Cear\u00e1 (CE)",
        "Distrito Federal (DF)",
        "Esp\u00edrito Santo (ES)",
        "Goi\u00e1s (GO)",
        "Maranh\u00e3o (MA)",
        "Mato Grosso (MT)",
        "Mato Grosso do Sul (MS)",
        "Minas Gerais (MG)",
        "Par\u00e1 (PA)",
        "Para\u00edba (PB)",
        "Paran\u00e1 (PR)",
        "Pernambuco (PE)",
        "Piau\u00ed (PI)",
        "Rio de Janeiro (RJ)",
        "Rio Grande do Norte (RN)",
        "Rio Grande do Sul (RS)",
        "Rond\u00f4nia (RO)",
        "Roraima (RR)",
        "Santa Catarina (SC)",
        "S\u00e3o Paulo (SP)",
        "Sergipe (SE)",
        "Tocantins (TO)"
      ],
      "index": [
        "Menos de 1.000",
        "Entre 1.001 e 2.000",
        "Entre 2.001 e 3.000",
        "Entre 3.001 e 4.000",
        "Entre 4.001 e 5.000",
        "Entre 5.001 e 6.000",
        "Entre 6.001 e 7.000",
        "Entre 7.001 e 9.000",
        "Entre 9.001 e 12.000",
        "Entre 12.001 e 15.000",
        "Entre 15.001 e 20.000",
        "Entre 20.001 e 30.000",
        "Entre 30.001 e 40.000",
        "Entre 40.001 e 50.000",
        "Acima de 50.000"
      ],
      "data": [
        [
          1.0,
          2.0,
          null,
          2.0,
          9,
          15,
          9.0,
          10.0,
          5.0,
          1.0,
          null,
          4.0,
          27,
          2.0,
          8.0,
          7,
          21.0,
          null,
          22,
          8.0,
          15,
          2.0,
          null,
          10,
          52,
          2.0,
          4.0
        ],
        [
          2.0, 9.0, 1.0, 13.0, 49, 64, 21.0, 19.0, 27.0, 8.0, 6.0, 12.0, 124,
          10.0, 16.0, 63, 64.0, 5.0, 100, 16.0, 71, 4.0, 1.0, 62, 320, 21.0, 7.0
        ],
        [
          2.0,
          11.0,
          null,
          10.0,
          40,
          53,
          28.0,
          23.0,
          23.0,
          10.0,
          13.0,
          20.0,
          129,
          16.0,
          18.0,
          102,
          54.0,
          15.0,
          94,
          14.0,
          108,
          6.0,
          null,
          87,
          416,
          11.0,
          5.0
        ],
        [
          null,
          7.0,
          1.0,
          12.0,
          52,
          58,
          26.0,
          28.0,
          30.0,
          13.0,
          9.0,
          20.0,
          147,
          22.0,
          26.0,
          95,
          49.0,
          10.0,
          75,
          19.0,
          66,
          3.0,
          null,
          99,
          401,
          10.0,
          2.0
        ],
        [
          null,
          12.0,
          1.0,
          16.0,
          28,
          42,
          24.0,
          25.0,
          24.0,
          5.0,
          11.0,
          15.0,
          130,
          15.0,
          27.0,
          82,
          37.0,
          13.0,
          94,
          17.0,
          69,
          10.0,
          null,
          79,
          357,
          7.0,
          8.0
        ],
        [
          2.0,
          9.0,
          null,
          14.0,
          30,
          36,
          27.0,
          21.0,
          27.0,
          12.0,
          12.0,
          8.0,
          119,
          11.0,
          12.0,
          81,
          21.0,
          8.0,
          61,
          23.0,
          84,
          6.0,
          1.0,
          59,
          340,
          12.0,
          7.0
        ],
        [
          null,
          6.0,
          null,
          9.0,
          23,
          25,
          25.0,
          13.0,
          14.0,
          6.0,
          5.0,
          6.0,
          91,
          11.0,
          12.0,
          68,
          28.0,
          3.0,
          61,
          11.0,
          44,
          6.0,
          null,
          56,
          288,
          6.0,
          5.0
        ],
        [
          2.0, 7.0, 1.0, 15.0, 42, 44, 55.0, 22.0, 24.0, 6.0, 11.0, 18.0, 161,
          13.0, 20.0, 98, 29.0, 8.0, 88, 10.0, 89, 4.0, 1.0, 93, 403, 18.0, 6.0
        ],
        [
          3.0,
          5.0,
          null,
          4.0,
          33,
          42,
          62.0,
          19.0,
          35.0,
          19.0,
          13.0,
          18.0,
          149,
          8.0,
          26.0,
          121,
          39.0,
          5.0,
          80,
          16.0,
          82,
          7.0,
          null,
          99,
          463,
          3.0,
          6.0
        ],
        [
          null,
          5.0,
          null,
          4.0,
          14,
          20,
          25.0,
          10.0,
          15.0,
          3.0,
          11.0,
          3.0,
          84,
          5.0,
          7.0,
          62,
          14.0,
          1.0,
          59,
          6.0,
          49,
          1.0,
          1.0,
          39,
          289,
          4.0,
          5.0
        ],
        [
          null,
          1.0,
          null,
          2.0,
          13,
          15,
          17.0,
          7.0,
          16.0,
          4.0,
          5.0,
          3.0,
          57,
          5.0,
          5.0,
          43,
          10.0,
          1.0,
          41,
          2.0,
          25,
          1.0,
          null,
          37,
          195,
          2.0,
          1.0
        ],
        [
          null,
          2.0,
          null,
          1.0,
          4,
          8,
          11.0,
          3.0,
          9.0,
          1.0,
          2.0,
          3.0,
          33,
          3.0,
          2.0,
          18,
          6.0,
          1.0,
          22,
          3.0,
          14,
          null,
          null,
          28,
          108,
          null,
          null
        ],
        [
          null,
          1.0,
          null,
          null,
          2,
          3,
          2.0,
          3.0,
          3.0,
          null,
          null,
          1.0,
          12,
          null,
          2.0,
          12,
          1.0,
          null,
          8,
          1.0,
          7,
          null,
          null,
          14,
          38,
          1.0,
          null
        ],
        [
          null,
          null,
          null,
          null,
          2,
          6,
          null,
          3.0,
          null,
          null,
          null,
          null,
          4,
          null,
          null,
          5,
          null,
          null,
          1,
          1.0,
          5,
          null,
          null,
          4,
          14,
          null,
          null
        ],
        [
          1.0,
          null,
          null,
          null,
          1,
          3,
          null,
          null,
          2.0,
          null,
          null,
          null,
          8,
          1.0,
          null,
          3,
          null,
          null,
          6,
          null,
          1,
          null,
          null,
          4,
          17,
          null,
          null
        ]
      ]
    },
    "salary_by_outside_brasil": {
      "columns": ["Fora do Brasil"],
      "index": [
        "Menos de 1.000",
        "Entre 1.001 e 2.000",
        "Entre 2.001 e 3.000",
        "Entre 3.001 e 4.000",
        "Entre 4.001 e 5.000",
        "Entre 5.001 e 6.000",
        "Entre 6.001 e 7.000",
        "Entre 7.001 e 9.000",
        "Entre 9.001 e 12.000",
        "Entre 12.001 e 15.000",
        "Entre 15.001 e 20.000",
        "Entre 20.001 e 30.000",
        "Entre 30.001 e 40.000",
        "Entre 40.001 e 50.000",
        "Acima de 50.000"
      ],
      "data": [
        [2],
        [3],
        [1],
        [4],
        [4],
        [3],
        [8],
        [15],
        [24],
        [30],
        [21],
        [28],
        [26],
        [16],
        [8]
      ]
    },
    "salary_by_back_to_brazil": {
      "columns": ["Sim", "N\u00e3o", "Talvez"],
      "index": [
        "Menos de 1.000",
        "Entre 1.001 e 2.000",
        "Entre 2.001 e 3.000",
        "Entre 3.001 e 4.000",
        "Entre 4.001 e 5.000",
        "Entre 5.001 e 6.000",
        "Entre 6.001 e 7.000",
        "Entre 7.001 e 9.000",
        "Entre 9.001 e 12.000",
        "Entre 12.001 e 15.000",
        "Entre 15.001 e 20.000",
        "Entre 20.001 e 30.000",
        "Entre 30.001 e 40.000",
        "Entre 40.001 e 50.000",
        "Acima de 50.000"
      ],
      "data": [
        [null, 1, 1.0],
        [null, 2, 1.0],
        [null, 1, null],
        [1.0, 2, 1.0],
        [null, 3, 1.0],
        [null, 3, null],
        [null, 8, null],
        [1.0, 8, 6.0],
        [4.0, 12, 8.0],
        [3.0, 20, 7.0],
        [3.0, 15, 3.0],
        [3.0, 15, 10.0],
        [2.0, 16, 8.0],
        [4.0, 11, 1.0],
        [null, 5, 3.0]
      ]
    },
    "salary_by_graduation": {
      "columns": [
        "N\u00e3o fiz faculdade",
        "Superior em andamento",
        "Superior incompleto",
        "Superior completo",
        "P\u00f3s-gradua\u00e7\u00e3o / MBA",
        "Mestrado / Doutorado"
      ],
      "index": [
        "Menos de 1.000",
        "Entre 1.001 e 2.000",
        "Entre 2.001 e 3.000",
        "Entre 3.001 e 4.000",
        "Entre 4.001 e 5.000",
        "Entre 5.001 e 6.000",
        "Entre 6.001 e 7.000",
        "Entre 7.001 e 9.000",
        "Entre 9.001 e 12.000",
        "Entre 12.001 e 15.000",
        "Entre 15.001 e 20.000",
        "Entre 20.001 e 30.000",
        "Entre 30.001 e 40.000",
        "Entre 40.001 e 50.000",
        "Acima de 50.000"
      ],
      "data": [
        [37, 147, 25, 21, 8, 2],
        [117, 684, 103, 185, 23, 6],
        [124, 582, 118, 420, 56, 9],
        [111, 449, 148, 490, 70, 16],
        [77, 341, 133, 488, 91, 22],
        [62, 231, 111, 500, 121, 21],
        [38, 161, 86, 394, 122, 29],
        [51, 179, 139, 644, 252, 38],
        [52, 136, 156, 648, 331, 58],
        [30, 42, 77, 373, 209, 35],
        [30, 34, 59, 234, 141, 31],
        [23, 22, 33, 142, 71, 19],
        [12, 6, 15, 65, 28, 11],
        [5, 3, 12, 29, 11, 1],
        [8, 3, 6, 24, 7, 7]
      ]
    },
    "salary_by_foreign_countries": {
      "columns": [
        "INGLATERRA",
        "ARGENTINA",
        "PORTUGAL",
        "IRLANDA",
        "ESPANHA",
        "IT\u00c1LIA",
        "PA\u00cdSES BAIXOS",
        "CANAD\u00c1",
        "DINAMARCA",
        "ALEMANHA",
        "ESC\u00d3CIA",
        "FRAN\u00c7A",
        "EUA",
        "REINO UNIDO",
        "SU\u00cd\u00c7A",
        "LIECHTENSTEIN",
        "B\u00c9LGICA",
        "JAP\u00c3O",
        "LUXEMBURGO",
        "\u00c1USTRIA",
        "URUGUAI",
        "HOLANDA",
        "MO\u00c7AMBIQUE",
        "ANGOLA",
        "PARAGUAI",
        "AUSTRALIA",
        "EL SALVADOR",
        "COL\u00d4MBIA",
        "NOVA ZEL\u00c2NDIA",
        "MALTA",
        "N\u00d4MADE",
        "MONTENEGRO"
      ],
      "index": [
        "Menos de 1.000",
        "Entre 1.001 e 2.000",
        "Entre 2.001 e 3.000",
        "Entre 3.001 e 4.000",
        "Entre 4.001 e 5.000",
        "Entre 5.001 e 6.000",
        "Entre 6.001 e 7.000",
        "Entre 7.001 e 9.000",
        "Entre 9.001 e 12.000",
        "Entre 12.001 e 15.000",
        "Entre 15.001 e 20.000",
        "Entre 20.001 e 30.000",
        "Entre 30.001 e 40.000",
        "Entre 40.001 e 50.000",
        "Acima de 50.000"
      ],
      "data": [
        [
          null,
          null,
          1.0,
          null,
          null,
          null,
          null,
          1.0,
          null,
          null,
          null,
          null,
          null,
          null,
          null,
          null,
          null,
          null,
          null,
          null,
          null,
          null,
          null,
          null,
          null,
          null,
          null,
          null,
          null,
          null,
          null,
          null
        ],
        [
          null,
          null,
          null,
          null,
          null,
          null,
          null,
          null,
          null,
          null,
          null,
          null,
          1.0,
          null,
          null,
          null,
          null,
          null,
          null,
          null,
          null,
          null,
          1.0,
          1.0,
          null,
          null,
          null,
          null,
          null,
          null,
          null,
          null
        ],
        [
          null,
          null,
          1.0,
          null,
          null,
          null,
          null,
          null,
          null,
          null,
          null,
          null,
          null,
          null,
          null,
          null,
          null,
          null,
          null,
          null,
          null,
          null,
          null,
          null,
          null,
          null,
          null,
          null,
          null,
          null,
          null,
          null
        ],
        [
          1.0,
          null,
          1.0,
          null,
          null,
          null,
          null,
          null,
          null,
          null,
          null,
          null,
          null,
          null,
          null,
          null,
          null,
          null,
          null,
          null,
          null,
          null,
          1.0,
          1.0,
          null,
          null,
          null,
          null,
          null,
          null,
          null,
          null
        ],
        [
          null,
          null,
          2.0,
          null,
          null,
          null,
          null,
          null,
          null,
          1.0,
          null,
          null,
          null,
          null,
          null,
          null,
          null,
          null,
          null,
          null,
          1.0,
          null,
          null,
          null,
          null,
          null,
          null,
          null,
          null,
          null,
          null,
          null
        ],
        [
          null,
          null,
          1.0,
          null,
          null,
          1.0,
          null,
          null,
          null,
          null,
          null,
          null,
          null,
          null,
          null,
          null,
          null,
          1.0,
          null,
          null,
          null,
          null,
          null,
          null,
          null,
          null,
          null,
          null,
          null,
          null,
          null,
          null
        ],
        [
          null,
          null,
          7.0,
          null,
          null,
          null,
          null,
          null,
          null,
          null,
          null,
          null,
          1.0,
          null,
          null,
          null,
          null,
          null,
          null,
          null,
          null,
          null,
          null,
          null,
          null,
          null,
          null,
          null,
          null,
          null,
          null,
          null
        ],
        [
          null,
          null,
          14.0,
          null,
          null,
          1.0,
          null,
          null,
          null,
          null,
          null,
          null,
          null,
          null,
          null,
          null,
          null,
          null,
          null,
          null,
          null,
          null,
          null,
          null,
          null,
          null,
          null,
          null,
          null,
          null,
          null,
          null
        ],
        [
          null,
          1.0,
          15.0,
          1.0,
          null,
          1.0,
          null,
          null,
          null,
          null,
          null,
          1.0,
          null,
          null,
          null,
          null,
          null,
          null,
          null,
          null,
          null,
          null,
          null,
          3.0,
          2.0,
          null,
          null,
          null,
          null,
          null,
          null,
          null
        ],
        [
          null,
          1.0,
          18.0,
          2.0,
          2.0,
          null,
          null,
          1.0,
          null,
          1.0,
          null,
          null,
          null,
          1.0,
          null,
          null,
          null,
          1.0,
          null,
          null,
          null,
          null,
          null,
          null,
          null,
          null,
          1.0,
          null,
          null,
          null,
          null,
          null
        ],
        [
          null,
          null,
          11.0,
          2.0,
          null,
          null,
          null,
          3.0,
          null,
          null,
          1.0,
          null,
          null,
          null,
          null,
          null,
          null,
          3.0,
          null,
          null,
          null,
          null,
          null,
          null,
          null,
          null,
          null,
          null,
          null,
          1.0,
          null,
          null
        ],
        [
          1.0,
          null,
          null,
          1.0,
          1.0,
          null,
          3.0,
          6.0,
          null,
          4.0,
          null,
          1.0,
          1.0,
          1.0,
          1.0,
          1.0,
          1.0,
          1.0,
          1.0,
          1.0,
          null,
          3.0,
          null,
          null,
          null,
          null,
          null,
          null,
          null,
          null,
          null,
          null
        ],
        [
          3.0,
          null,
          4.0,
          1.0,
          null,
          null,
          1.0,
          1.0,
          1.0,
          6.0,
          null,
          null,
          null,
          null,
          null,
          null,
          1.0,
          1.0,
          null,
          null,
          null,
          2.0,
          null,
          1.0,
          null,
          1.0,
          null,
          null,
          null,
          null,
          null,
          1.0
        ],
        [
          null,
          null,
          null,
          1.0,
          null,
          1.0,
          null,
          5.0,
          null,
          2.0,
          null,
          null,
          1.0,
          1.0,
          null,
          null,
          null,
          null,
          2.0,
          null,
          null,
          1.0,
          null,
          null,
          null,
          null,
          null,
          null,
          1.0,
          null,
          1.0,
          null
        ],
        [
          null,
          null,
          null,
          1.0,
          null,
          null,
          1.0,
          1.0,
          null,
          null,
          null,
          null,
          2.0,
          null,
          null,
          null,
          null,
          null,
          null,
          null,
          null,
          null,
          null,
          1.0,
          1.0,
          null,
          null,
          1.0,
          null,
          null,
          null,
          null
        ]
      ]
    },
    "salary_by_platforms": {
      "columns": ["Web", "Mobile", "Desktop", "Embarcados", "Outra"],
      "index": [
        "Menos de 1.000",
        "Entre 1.001 e 2.000",
        "Entre 2.001 e 3.000",
        "Entre 3.001 e 4.000",
        "Entre 4.001 e 5.000",
        "Entre 5.001 e 6.000",
        "Entre 6.001 e 7.000",
        "Entre 7.001 e 9.000",
        "Entre 9.001 e 12.000",
        "Entre 12.001 e 15.000",
        "Entre 15.001 e 20.000",
        "Entre 20.001 e 30.000",
        "Entre 30.001 e 40.000",
        "Entre 40.001 e 50.000",
        "Acima de 50.000"
      ],
      "data": [
        [83, 46, 54, 7, 8],
        [336, 204, 200, 30, 45],
        [416, 265, 241, 33, 46],
        [404, 270, 210, 27, 46],
        [402, 266, 205, 39, 45],
        [389, 270, 192, 44, 45],
        [297, 205, 143, 33, 45],
        [485, 291, 268, 62, 72],
        [600, 411, 321, 77, 99],
        [349, 244, 197, 57, 54],
        [234, 165, 125, 40, 49],
        [138, 104, 69, 26, 29],
        [55, 43, 28, 11, 13],
        [27, 24, 15, 1, 7],
        [28, 23, 17, 8, 10]
      ]
    },
    "salary_by_languages": {
      "columns": [
        "JAVASCRIPT",
        "JAVA",
        "C#",
        "PHP",
        "PYTHON",
        "TYPESCRIPT",
        "KOTLIN",
        "DART",
        "DELPHI",
        "RUBY",
        "GO",
        "SWIFT",
        "SQL",
        ".NET (CORE)",
        "BUBBLE",
        "C++",
        "APEX",
        "C",
        "PL/SQL",
        "ELIXIR",
        "ADVPL",
        "CLOJURE",
        "ABAP",
        "VISUAL BASIC 6",
        "HTML",
        "NO CODE",
        "POWER FX",
        "VB.NET",
        "COBOL",
        "SHELL",
        "PASCAL",
        "BASH",
        "PROGRESS",
        "SCALA",
        "ASP 3",
        "RUST",
        "CSS",
        "GENEXUS",
        "LUA",
        "GROOVY",
        "VBA",
        "SHELL SCRIPT",
        "POWER PLATFORM",
        "MAKER",
        "OUTSYSTEMS",
        "UNIFACE",
        "PERL",
        "YAML",
        "OBJECT PASCAL",
        "SQL SERVER",
        "POWERSHELL",
        "REACT",
        "TERRAFORM",
        "CENTURA",
        "R",
        "BI",
        "POWERAPPS",
        "SPARK",
        "SELENIUM",
        "HCL"
      ],
      "index": [
        "Menos de 1.000",
        "Entre 1.001 e 2.000",
        "Entre 2.001 e 3.000",
        "Entre 3.001 e 4.000",
        "Entre 4.001 e 5.000",
        "Entre 5.001 e 6.000",
        "Entre 6.001 e 7.000",
        "Entre 7.001 e 9.000",
        "Entre 9.001 e 12.000",
        "Entre 12.001 e 15.000",
        "Entre 15.001 e 20.000",
        "Entre 20.001 e 30.000",
        "Entre 30.001 e 40.000",
        "Entre 40.001 e 50.000",
        "Acima de 50.000"
      ],
      "data": [
        [
          94,
          34,
          18,
          44,
          24,
          5.0,
          1,
          4.0,
          2.0,
          6,
          null,
          null,
          2.0,
          null,
          1.0,
          null,
          null,
          1.0,
          null,
          null,
          null,
          null,
          null,
          null,
          2.0,
          2.0,
          null,
          null,
          1.0,
          null,
          null,
          null,
          null,
          null,
          1.0,
          null,
          null,
          null,
          null,
          null,
          null,
          null,
          null,
          null,
          null,
          null,
          null,
          null,
          null,
          null,
          null,
          null,
          null,
          null,
          null,
          1.0,
          null,
          null,
          null,
          null
        ],
        [
          382,
          177,
          143,
          172,
          98,
          46.0,
          10,
          26.0,
          15.0,
          8,
          9.0,
          7.0,
          7.0,
          3.0,
          8.0,
          4.0,
          3.0,
          6.0,
          3.0,
          2.0,
          1.0,
          null,
          1.0,
          2.0,
          5.0,
          1.0,
          2.0,
          null,
          null,
          1.0,
          1.0,
          null,
          2.0,
          1.0,
          1.0,
          1.0,
          3.0,
          null,
          3.0,
          null,
          1.0,
          null,
          1.0,
          null,
          1.0,
          null,
          null,
          null,
          1.0,
          null,
          null,
          null,
          null,
          1.0,
          1.0,
          null,
          null,
          null,
          null,
          null
        ],
        [
          483,
          182,
          163,
          181,
          87,
          53.0,
          14,
          31.0,
          27.0,
          17,
          9.0,
          6.0,
          12.0,
          6.0,
          9.0,
          5.0,
          6.0,
          7.0,
          4.0,
          1.0,
          3.0,
          null,
          2.0,
          1.0,
          1.0,
          null,
          3.0,
          null,
          null,
          null,
          1.0,
          null,
          null,
          null,
          2.0,
          null,
          1.0,
          null,
          1.0,
          1.0,
          3.0,
          null,
          null,
          null,
          null,
          null,
          null,
          null,
          null,
          null,
          1.0,
          null,
          null,
          1.0,
          null,
          null,
          1.0,
          null,
          1.0,
          null
        ],
        [
          475,
          184,
          144,
          159,
          89,
          70.0,
          19,
          32.0,
          20.0,
          21,
          9.0,
          12.0,
          10.0,
          5.0,
          11.0,
          4.0,
          9.0,
          3.0,
          3.0,
          2.0,
          1.0,
          1.0,
          1.0,
          2.0,
          3.0,
          2.0,
          1.0,
          null,
          null,
          null,
          1.0,
          null,
          1.0,
          1.0,
          1.0,
          null,
          2.0,
          null,
          null,
          null,
          1.0,
          1.0,
          null,
          null,
          1.0,
          2.0,
          1.0,
          null,
          null,
          1.0,
          1.0,
          null,
          null,
          null,
          null,
          1.0,
          null,
          null,
          1.0,
          null
        ],
        [
          374,
          181,
          171,
          137,
          78,
          43.0,
          22,
          32.0,
          28.0,
          20,
          9.0,
          7.0,
          15.0,
          6.0,
          10.0,
          11.0,
          4.0,
          5.0,
          6.0,
          1.0,
          1.0,
          null,
          1.0,
          3.0,
          1.0,
          1.0,
          1.0,
          5.0,
          3.0,
          1.0,
          2.0,
          null,
          null,
          null,
          null,
          null,
          null,
          null,
          2.0,
          1.0,
          null,
          null,
          null,
          null,
          null,
          null,
          null,
          1.0,
          1.0,
          null,
          null,
          1.0,
          null,
          null,
          null,
          null,
          null,
          null,
          null,
          null
        ],
        [
          331,
          178,
          135,
          116,
          80,
          49.0,
          31,
          20.0,
          19.0,
          13,
          10.0,
          11.0,
          6.0,
          10.0,
          11.0,
          7.0,
          4.0,
          2.0,
          2.0,
          4.0,
          1.0,
          null,
          2.0,
          1.0,
          null,
          1.0,
          1.0,
          1.0,
          null,
          null,
          3.0,
          1.0,
          null,
          null,
          null,
          null,
          null,
          1.0,
          null,
          1.0,
          1.0,
          null,
          null,
          null,
          null,
          null,
          1.0,
          null,
          1.0,
          1.0,
          null,
          1.0,
          null,
          null,
          null,
          null,
          1.0,
          null,
          null,
          null
        ],
        [
          246,
          142,
          127,
          78,
          65,
          35.0,
          28,
          14.0,
          15.0,
          12,
          15.0,
          9.0,
          4.0,
          7.0,
          8.0,
          3.0,
          5.0,
          6.0,
          2.0,
          3.0,
          8.0,
          1.0,
          null,
          2.0,
          1.0,
          2.0,
          1.0,
          1.0,
          null,
          2.0,
          1.0,
          null,
          2.0,
          1.0,
          1.0,
          1.0,
          null,
          null,
          null,
          null,
          null,
          null,
          null,
          1.0,
          1.0,
          null,
          1.0,
          null,
          null,
          null,
          null,
          1.0,
          null,
          null,
          1.0,
          null,
          null,
          null,
          null,
          null
        ],
        [
          360,
          284,
          202,
          118,
          99,
          47.0,
          35,
          25.0,
          21.0,
          24,
          15.0,
          20.0,
          15.0,
          8.0,
          9.0,
          8.0,
          5.0,
          6.0,
          7.0,
          5.0,
          5.0,
          4.0,
          1.0,
          1.0,
          1.0,
          null,
          3.0,
          null,
          null,
          3.0,
          null,
          4.0,
          1.0,
          2.0,
          1.0,
          null,
          null,
          null,
          null,
          1.0,
          null,
          2.0,
          1.0,
          1.0,
          null,
          null,
          null,
          null,
          null,
          null,
          null,
          null,
          null,
          null,
          null,
          null,
          null,
          null,
          null,
          null
        ],
        [
          347,
          312,
          237,
          98,
          90,
          51.0,
          54,
          26.0,
          25.0,
          23,
          22.0,
          20.0,
          11.0,
          14.0,
          6.0,
          9.0,
          7.0,
          4.0,
          8.0,
          4.0,
          8.0,
          7.0,
          4.0,
          4.0,
          null,
          4.0,
          null,
          1.0,
          1.0,
          null,
          null,
          null,
          2.0,
          1.0,
          null,
          1.0,
          null,
          3.0,
          null,
          null,
          null,
          1.0,
          1.0,
          2.0,
          null,
          1.0,
          null,
          1.0,
          null,
          null,
          null,
          null,
          1.0,
          1.0,
          1.0,
          null,
          null,
          null,
          null,
          null
        ],
        [
          171,
          191,
          134,
          45,
          50,
          24.0,
          24,
          13.0,
          15.0,
          10,
          10.0,
          18.0,
          4.0,
          17.0,
          7.0,
          5.0,
          10.0,
          5.0,
          4.0,
          3.0,
          5.0,
          1.0,
          4.0,
          null,
          1.0,
          null,
          2.0,
          2.0,
          2.0,
          1.0,
          null,
          1.0,
          null,
          1.0,
          null,
          null,
          1.0,
          2.0,
          null,
          1.0,
          null,
          null,
          null,
          null,
          1.0,
          null,
          null,
          1.0,
          null,
          1.0,
          1.0,
          null,
          1.0,
          null,
          null,
          null,
          null,
          null,
          null,
          1.0
        ],
        [
          125,
          105,
          86,
          43,
          46,
          22.0,
          17,
          5.0,
          5.0,
          9,
          21.0,
          12.0,
          4.0,
          6.0,
          null,
          3.0,
          5.0,
          2.0,
          2.0,
          3.0,
          3.0,
          4.0,
          4.0,
          1.0,
          1.0,
          1.0,
          null,
          1.0,
          null,
          null,
          null,
          1.0,
          null,
          null,
          null,
          1.0,
          null,
          null,
          null,
          1.0,
          null,
          null,
          1.0,
          null,
          null,
          null,
          null,
          null,
          null,
          null,
          null,
          null,
          1.0,
          null,
          null,
          null,
          null,
          1.0,
          null,
          null
        ],
        [
          86,
          50,
          36,
          19,
          39,
          11.0,
          5,
          3.0,
          2.0,
          11,
          17.0,
          7.0,
          1.0,
          5.0,
          3.0,
          6.0,
          2.0,
          2.0,
          1.0,
          3.0,
          null,
          2.0,
          null,
          null,
          null,
          1.0,
          null,
          1.0,
          null,
          1.0,
          null,
          1.0,
          null,
          null,
          null,
          1.0,
          null,
          null,
          null,
          null,
          null,
          1.0,
          null,
          null,
          null,
          null,
          null,
          null,
          null,
          null,
          null,
          null,
          null,
          null,
          null,
          null,
          null,
          null,
          null,
          1.0
        ],
        [
          42,
          15,
          7,
          5,
          27,
          5.0,
          5,
          1.0,
          null,
          5,
          6.0,
          2.0,
          null,
          1.0,
          1.0,
          4.0,
          null,
          null,
          1.0,
          3.0,
          null,
          2.0,
          null,
          null,
          null,
          null,
          null,
          null,
          1.0,
          null,
          null,
          null,
          null,
          null,
          null,
          null,
          null,
          null,
          null,
          null,
          null,
          null,
          null,
          null,
          null,
          null,
          null,
          null,
          null,
          null,
          null,
          null,
          null,
          null,
          null,
          null,
          null,
          null,
          null,
          null
        ],
        [
          26,
          6,
          6,
          9,
          1,
          3.0,
          3,
          2.0,
          null,
          2,
          3.0,
          null,
          null,
          1.0,
          null,
          2.0,
          null,
          null,
          null,
          1.0,
          null,
          null,
          null,
          null,
          null,
          null,
          null,
          null,
          1.0,
          null,
          null,
          null,
          null,
          1.0,
          null,
          null,
          null,
          null,
          null,
          null,
          null,
          null,
          null,
          null,
          null,
          null,
          null,
          null,
          null,
          null,
          null,
          null,
          null,
          null,
          null,
          null,
          null,
          1.0,
          null,
          null
        ],
        [
          15,
          7,
          5,
          3,
          8,
          null,
          1,
          null,
          null,
          4,
          3.0,
          2.0,
          null,
          null,
          1.0,
          1.0,
          1.0,
          null,
          null,
          4.0,
          null,
          null,
          null,
          null,
          null,
          null,
          null,
          null,
          null,
          null,
          null,
          null,
          null,
          null,
          null,
          2.0,
          null,
          null,
          null,
          null,
          null,
          null,
          null,
          null,
          null,
          null,
          null,
          null,
          null,
          null,
          null,
          null,
          null,
          null,
          null,
          null,
          null,
          null,
          null,
          null
        ]
      ]
    },
    "salary_by_frameworks": {
      "columns": [
        "REACT",
        "NODE.JS",
        "ANGULAR",
        "VUE.JS",
        "SPRING",
        "LARAVEL",
        ".NET",
        "FLUTTER",
        "SPRING BOOT",
        "REACT NATIVE",
        "DJANGO",
        "NEXT.JS",
        "NEST.JS",
        ".NET CORE",
        "RAILS",
        "DOCKER",
        "AWS",
        "JQUERY",
        "FLASK",
        "BOOTSTRAP",
        "EXPRESS",
        "MYSQL",
        "IONIC",
        "ANGULARJS",
        "MONGODB",
        "KUBERNETES",
        "ANDROID",
        "KAFKA",
        "CODEIGNITER",
        "FASTAPI",
        "ASP.NET",
        "GIT",
        "PANDAS",
        "QUARKUS",
        "SQL SERVER",
        "SYMPHONY",
        "WORDPRESS",
        "GRAPHQL",
        "HIBERNATE",
        "POSTGRESQL",
        ".NET FRAMEWORK",
        "KOTLIN",
        "JSF",
        "BUBBLE",
        "XAMARIN",
        "REACT-NATIVE",
        "ASP.NET CORE",
        "AZURE",
        "SPRING FRAMEWORK",
        "POSTGRES",
        "SPARK",
        "LUMEN",
        "RABBITMQ",
        "NUXT",
        "PHOENIX",
        "SERVERLESS",
        "TERRAFORM",
        "ORACLE",
        "REDIS",
        "REACT JS"
      ],
      "index": [
        "Menos de 1.000",
        "Entre 1.001 e 2.000",
        "Entre 2.001 e 3.000",
        "Entre 3.001 e 4.000",
        "Entre 4.001 e 5.000",
        "Entre 5.001 e 6.000",
        "Entre 6.001 e 7.000",
        "Entre 7.001 e 9.000",
        "Entre 9.001 e 12.000",
        "Entre 12.001 e 15.000",
        "Entre 15.001 e 20.000",
        "Entre 20.001 e 30.000",
        "Entre 30.001 e 40.000",
        "Entre 40.001 e 50.000",
        "Acima de 50.000"
      ],
      "data": [
        [
          57,
          40,
          25,
          14,
          9,
          21,
          6,
          9,
          8.0,
          4,
          10,
          2,
          null,
          2.0,
          5,
          2.0,
          null,
          6.0,
          5.0,
          10.0,
          3,
          3.0,
          1.0,
          null,
          1.0,
          null,
          null,
          null,
          2.0,
          null,
          2.0,
          null,
          1.0,
          null,
          1.0,
          1.0,
          null,
          null,
          1.0,
          2.0,
          null,
          null,
          2.0,
          null,
          null,
          2.0,
          null,
          null,
          null,
          null,
          null,
          null,
          null,
          null,
          null,
          null,
          null,
          null,
          null,
          1.0
        ],
        [
          249,
          185,
          134,
          81,
          47,
          82,
          67,
          55,
          39.0,
          37,
          32,
          20,
          12.0,
          6.0,
          7,
          17.0,
          8.0,
          32.0,
          11.0,
          33.0,
          9,
          16.0,
          7.0,
          4.0,
          6.0,
          null,
          2.0,
          3.0,
          9.0,
          4.0,
          10.0,
          8.0,
          8.0,
          4.0,
          7.0,
          7.0,
          11.0,
          6.0,
          6.0,
          4.0,
          3.0,
          null,
          7.0,
          2.0,
          4.0,
          3.0,
          3.0,
          3.0,
          5.0,
          7.0,
          1.0,
          2.0,
          null,
          5.0,
          1.0,
          2.0,
          1.0,
          2.0,
          2.0,
          2.0
        ],
        [
          319,
          233,
          177,
          136,
          58,
          101,
          61,
          60,
          51.0,
          52,
          31,
          36,
          28.0,
          19.0,
          21,
          17.0,
          7.0,
          32.0,
          18.0,
          35.0,
          16,
          11.0,
          14.0,
          14.0,
          7.0,
          3.0,
          5.0,
          2.0,
          15.0,
          5.0,
          9.0,
          9.0,
          4.0,
          4.0,
          13.0,
          6.0,
          7.0,
          5.0,
          7.0,
          7.0,
          5.0,
          2.0,
          6.0,
          2.0,
          7.0,
          4.0,
          5.0,
          5.0,
          4.0,
          2.0,
          1.0,
          3.0,
          1.0,
          1.0,
          1.0,
          null,
          1.0,
          2.0,
          3.0,
          7.0
        ],
        [
          386,
          268,
          175,
          118,
          63,
          103,
          65,
          69,
          40.0,
          54,
          34,
          33,
          26.0,
          17.0,
          22,
          22.0,
          10.0,
          25.0,
          22.0,
          30.0,
          15,
          15.0,
          7.0,
          15.0,
          6.0,
          4.0,
          3.0,
          3.0,
          20.0,
          8.0,
          10.0,
          7.0,
          6.0,
          4.0,
          2.0,
          9.0,
          8.0,
          2.0,
          6.0,
          7.0,
          3.0,
          6.0,
          6.0,
          5.0,
          1.0,
          5.0,
          7.0,
          3.0,
          6.0,
          4.0,
          2.0,
          3.0,
          5.0,
          4.0,
          1.0,
          2.0,
          null,
          3.0,
          2.0,
          3.0
        ],
        [
          308, 244, 185, 99, 68, 95, 79, 55, 55.0, 52, 28, 31, 19.0, 26.0, 16,
          23.0, 12.0, 16.0, 11.0, 12.0, 8, 19.0, 5.0, 6.0, 11.0, 4.0, 3.0, 5.0,
          10.0, 6.0, 8.0, 7.0, 12.0, 8.0, 8.0, 5.0, 6.0, 2.0, 7.0, 7.0, 4.0, 2.0,
          4.0, 6.0, 1.0, 4.0, 7.0, 2.0, 1.0, 5.0, 3.0, 5.0, 4.0, 8.0, 1.0, 5.0,
          1.0, 6.0, 4.0, 5.0
        ],
        [
          284, 208, 176, 86, 76, 67, 56, 60, 56.0, 48, 36, 31, 21.0, 15.0, 15,
          15.0, 23.0, 12.0, 17.0, 9.0, 10, 8.0, 9.0, 10.0, 9.0, 1.0, 7.0, 8.0,
          7.0, 5.0, 6.0, 5.0, 2.0, 5.0, 2.0, 5.0, 4.0, 6.0, 1.0, 4.0, 5.0, 7.0,
          5.0, 7.0, 2.0, 5.0, 4.0, 1.0, 4.0, 4.0, 2.0, 4.0, 3.0, 5.0, 4.0, 4.0,
          2.0, 2.0, 1.0, 3.0
        ],
        [
          220,
          177,
          144,
          72,
          67,
          52,
          48,
          44,
          42.0,
          38,
          22,
          18,
          26.0,
          24.0,
          18,
          12.0,
          15.0,
          12.0,
          8.0,
          3.0,
          9,
          12.0,
          11.0,
          5.0,
          11.0,
          7.0,
          12.0,
          5.0,
          2.0,
          6.0,
          2.0,
          9.0,
          4.0,
          4.0,
          1.0,
          null,
          3.0,
          4.0,
          3.0,
          5.0,
          5.0,
          2.0,
          4.0,
          6.0,
          3.0,
          null,
          1.0,
          3.0,
          5.0,
          2.0,
          6.0,
          4.0,
          null,
          6.0,
          3.0,
          3.0,
          1.0,
          2.0,
          2.0,
          3.0
        ],
        [
          325, 285, 223, 99, 124, 80, 90, 68, 77.0, 57, 36, 34, 38.0, 30.0, 31,
          27.0, 29.0, 18.0, 25.0, 14.0, 14, 13.0, 12.0, 23.0, 9.0, 14.0, 11.0,
          16.0, 4.0, 12.0, 4.0, 9.0, 10.0, 10.0, 10.0, 6.0, 3.0, 9.0, 6.0, 5.0,
          7.0, 3.0, 9.0, 7.0, 4.0, 6.0, 2.0, 2.0, 3.0, 3.0, 4.0, 4.0, 7.0, 1.0,
          4.0, 5.0, 4.0, 4.0, 5.0, 2.0
        ],
        [
          339, 304, 259, 108, 127, 79, 94, 89, 87.0, 55, 34, 36, 34.0, 40.0, 20,
          23.0, 30.0, 16.0, 16.0, 6.0, 11, 9.0, 15.0, 9.0, 15.0, 17.0, 16.0, 19.0,
          8.0, 18.0, 11.0, 8.0, 13.0, 14.0, 12.0, 6.0, 8.0, 10.0, 14.0, 6.0, 12.0,
          11.0, 4.0, 7.0, 8.0, 8.0, 6.0, 3.0, 8.0, 5.0, 7.0, 2.0, 6.0, 1.0, 5.0,
          3.0, 3.0, 5.0, 5.0, 2.0
        ],
        [
          158,
          156,
          159,
          59,
          86,
          38,
          48,
          58,
          46.0,
          29,
          22,
          19,
          18.0,
          21.0,
          15,
          20.0,
          24.0,
          4.0,
          11.0,
          3.0,
          11,
          8.0,
          10.0,
          3.0,
          6.0,
          12.0,
          6.0,
          11.0,
          4.0,
          4.0,
          4.0,
          4.0,
          3.0,
          6.0,
          4.0,
          3.0,
          4.0,
          2.0,
          4.0,
          1.0,
          5.0,
          10.0,
          3.0,
          3.0,
          8.0,
          2.0,
          3.0,
          3.0,
          null,
          4.0,
          3.0,
          5.0,
          5.0,
          2.0,
          3.0,
          4.0,
          7.0,
          5.0,
          3.0,
          2.0
        ],
        [
          129,
          128,
          92,
          47,
          52,
          31,
          38,
          25,
          28.0,
          18,
          9,
          11,
          19.0,
          12.0,
          12,
          12.0,
          19.0,
          1.0,
          7.0,
          1.0,
          9,
          3.0,
          6.0,
          2.0,
          5.0,
          12.0,
          9.0,
          7.0,
          null,
          1.0,
          5.0,
          4.0,
          3.0,
          3.0,
          3.0,
          7.0,
          4.0,
          7.0,
          3.0,
          6.0,
          4.0,
          3.0,
          2.0,
          1.0,
          2.0,
          2.0,
          2.0,
          7.0,
          null,
          2.0,
          5.0,
          4.0,
          1.0,
          2.0,
          2.0,
          2.0,
          2.0,
          2.0,
          5.0,
          2.0
        ],
        [
          96,
          73,
          55,
          29,
          20,
          12,
          16,
          20,
          10.0,
          10,
          12,
          6,
          6.0,
          6.0,
          14,
          7.0,
          10.0,
          5.0,
          8.0,
          2.0,
          4,
          1.0,
          5.0,
          3.0,
          5.0,
          10.0,
          5.0,
          2.0,
          null,
          5.0,
          2.0,
          1.0,
          2.0,
          5.0,
          2.0,
          3.0,
          null,
          1.0,
          1.0,
          null,
          2.0,
          3.0,
          1.0,
          2.0,
          2.0,
          1.0,
          1.0,
          6.0,
          3.0,
          1.0,
          1.0,
          null,
          2.0,
          null,
          1.0,
          1.0,
          6.0,
          1.0,
          null,
          1.0
        ],
        [
          46,
          32,
          14,
          8,
          8,
          4,
          3,
          9,
          4.0,
          12,
          14,
          8,
          3.0,
          null,
          4,
          2.0,
          7.0,
          1.0,
          3.0,
          null,
          2,
          2.0,
          null,
          null,
          2.0,
          4.0,
          4.0,
          null,
          null,
          1.0,
          null,
          2.0,
          1.0,
          null,
          null,
          null,
          null,
          1.0,
          null,
          1.0,
          null,
          4.0,
          null,
          1.0,
          null,
          1.0,
          null,
          1.0,
          null,
          null,
          1.0,
          null,
          1.0,
          null,
          4.0,
          2.0,
          3.0,
          null,
          2.0,
          1.0
        ],
        [
          26,
          18,
          5,
          4,
          1,
          6,
          2,
          4,
          2.0,
          6,
          1,
          2,
          3.0,
          1.0,
          3,
          3.0,
          2.0,
          null,
          null,
          null,
          1,
          null,
          1.0,
          null,
          null,
          2.0,
          1.0,
          null,
          null,
          null,
          null,
          null,
          null,
          1.0,
          1.0,
          2.0,
          1.0,
          4.0,
          null,
          null,
          null,
          null,
          null,
          null,
          1.0,
          null,
          null,
          1.0,
          null,
          null,
          2.0,
          null,
          null,
          null,
          1.0,
          null,
          3.0,
          null,
          null,
          null
        ],
        [
          16,
          10,
          3,
          2,
          4,
          1,
          3,
          4,
          null,
          2,
          4,
          1,
          null,
          null,
          5,
          null,
          2.0,
          null,
          1.0,
          1.0,
          2,
          null,
          null,
          null,
          null,
          null,
          null,
          null,
          null,
          null,
          null,
          null,
          null,
          1.0,
          null,
          null,
          1.0,
          null,
          null,
          null,
          null,
          1.0,
          null,
          null,
          1.0,
          null,
          null,
          null,
          1.0,
          null,
          null,
          null,
          null,
          null,
          3.0,
          null,
          null,
          null,
          null,
          null
        ]
      ]
    }
  }